Metadata-Version: 2.1
Name: autoenrich
Version: 2.1.1
Summary: Computational NMR Library
Home-page: https://github.com/wg12385/autoenrich_public
Author: Will Gerrard
Author-email: will.gerrard@bristol.ac.uk
License: UNKNOWN
Platform: UNKNOWN
Classifier: Programming Language :: Python :: 3
Classifier: License :: OSI Approved :: GNU Affero General Public License v3 or later (AGPLv3+)
Classifier: Operating System :: OS Independent
